odoo/addons/hr_contract_multi_job/README.rst
odoo/addons/hr_contract_multi_job/__init__.py
odoo/addons/hr_contract_multi_job/__manifest__.py
odoo/addons/hr_contract_multi_job/i18n/ar.po
odoo/addons/hr_contract_multi_job/i18n/de.po
odoo/addons/hr_contract_multi_job/i18n/es.po
odoo/addons/hr_contract_multi_job/i18n/fi.po
odoo/addons/hr_contract_multi_job/i18n/fr.po
odoo/addons/hr_contract_multi_job/i18n/hr.po
odoo/addons/hr_contract_multi_job/i18n/hr_contract_multi_job.pot
odoo/addons/hr_contract_multi_job/i18n/it.po
odoo/addons/hr_contract_multi_job/i18n/pt_BR.po
odoo/addons/hr_contract_multi_job/i18n/ro.po
odoo/addons/hr_contract_multi_job/i18n/sl.po
odoo/addons/hr_contract_multi_job/models/__init__.py
odoo/addons/hr_contract_multi_job/models/hr_contract.py
odoo/addons/hr_contract_multi_job/models/hr_contract_job.py
odoo/addons/hr_contract_multi_job/models/hr_job.py
odoo/addons/hr_contract_multi_job/readme/CONTRIBUTORS.rst
odoo/addons/hr_contract_multi_job/readme/DESCRIPTION.rst
odoo/addons/hr_contract_multi_job/readme/INSTALL.rst
odoo/addons/hr_contract_multi_job/readme/USAGE.rst
odoo/addons/hr_contract_multi_job/security/ir.model.access.csv
odoo/addons/hr_contract_multi_job/static/description/icon.png
odoo/addons/hr_contract_multi_job/static/description/index.html
odoo/addons/hr_contract_multi_job/tests/__init__.py
odoo/addons/hr_contract_multi_job/tests/test_hr_contract_multi_jobs.py
odoo/addons/hr_contract_multi_job/views/hr_contract_view.xml
odoo12_addon_hr_contract_multi_job-12.0.1.0.0.99.dev15.dist-info/METADATA
odoo12_addon_hr_contract_multi_job-12.0.1.0.0.99.dev15.dist-info/WHEEL
odoo12_addon_hr_contract_multi_job-12.0.1.0.0.99.dev15.dist-info/top_level.txt
odoo12_addon_hr_contract_multi_job-12.0.1.0.0.99.dev15.dist-info/RECORD
